dir2text/__init__.py
dir2text/cli/__init__.py
dir2text/cli/argparser.py
dir2text/cli/main.py
dir2text/cli/safe_writer.py
dir2text/cli/signal_handler.py
dir2text/dir2text.py
dir2text/exceptions.py
dir2text/exclusion_rules/__init__.py
dir2text/exclusion_rules/base_rules.py
dir2text/exclusion_rules/composite_rules.py
dir2text/exclusion_rules/git_rules.py
dir2text/exclusion_rules/size_rules.py
dir2text/file_content_printer.py
dir2text/file_system_tree/__init__.py
dir2text/file_system_tree/binary_action.py
dir2text/file_system_tree/binary_detector.py
dir2text/file_system_tree/file_identifier.py
dir2text/file_system_tree/file_system_node.py
dir2text/file_system_tree/file_system_tree.py
dir2text/file_system_tree/permission_action.py
dir2text/io/chunked_file_reader.py
dir2text/output_strategies/__init__.py
dir2text/output_strategies/base_strategy.py
dir2text/output_strategies/json_strategy.py
dir2text/output_strategies/xml_strategy.py
dir2text/token_counter.py
dir2text/types.py
dir2text-3.0.1.dist-info/LICENSE
dir2text-3.0.1.dist-info/METADATA
dir2text-3.0.1.dist-info/WHEEL
dir2text-3.0.1.dist-info/entry_points.txt
dir2text-3.0.1.dist-info/RECORD
