Metadata-Version: 2.1
Name: dir2text
Version: 3.0.1
Summary: A Python library and command-line tool for expressing directory structures and file contents in formats suitable for Large Language Models (LLMs). It combines directory tree visualization with file contents in a memory-efficient, streaming format.
Home-page: https://github.com/rlichtenwalter/dir2text.git
License: MIT
Keywords: large language model,LLM,token,tokenizer,SLOC,tree,code assistant
Author: Ryan N. Lichtenwalter
Author-email: rlichtenwalter@gmail.com
Maintainer: Ryan N. Lichtenwalter
Maintainer-email: rlichtenwalter@gmail.com
Requires-Python: >=3.9.1,<4.0
Classifier: Development Status :: 4 - Beta
Classifier: Intended Audience :: Developers
Classifier: License :: OSI Approved :: MIT License
Classifier: Programming Language :: Python :: 3
Classifier: Programming Language :: Python :: 3.10
Classifier: Programming Language :: Python :: 3.11
Classifier: Programming Language :: Python :: 3.12
Classifier: Programming Language :: Python :: 3.13
Classifier: Programming Language :: Python :: 3.9
Classifier: Topic :: Software Development
Provides-Extra: all
Provides-Extra: token-counting
Requires-Dist: anytree (>=2.12.0,<3.0.0)
Requires-Dist: humanfriendly (>=10.0,<11.0)
Requires-Dist: pathspec (>=0.12.1,<0.13.0)
Requires-Dist: tiktoken (>=0.6.0) ; extra == "token-counting" or extra == "all"
Project-URL: Repository, https://github.com/rlichtenwalter/dir2text.git
